pytestsysstats/__init__.py
pytestsysstats/plugin.py
pytestsysstats/py.typed
pytestsysstats/version.py
pytest_system_statistics-1.0.2.dist-info/LICENSE
pytest_system_statistics-1.0.2.dist-info/METADATA
pytest_system_statistics-1.0.2.dist-info/NOTICE
pytest_system_statistics-1.0.2.dist-info/WHEEL
pytest_system_statistics-1.0.2.dist-info/entry_points.txt
pytest_system_statistics-1.0.2.dist-info/top_level.txt
pytest_system_statistics-1.0.2.dist-info/RECORD
