Metadata-Version: 2.1
Name: pytest-system-statistics
Version: 1.0.2
Summary: Pytest plugin to track and report system usage statistics
Home-page: https://github.com/saltstack/pytest-system-statistics
Author: Pedro Algarvio
Author-email: pedro@algarvio.me
License: Apache Software License 2.0
Project-URL: Source, https://github.com/saltstack/pytest-system-statistics
Project-URL: Tracker, https://github.com/saltstack/pytest-system-statistics/issues
Project-URL: Documentation, https://pytest-system-statistics.readthedocs.io
Platform: unix
Platform: linux
Platform: osx
Platform: cygwin
Platform: win32
Classifier: Programming Language :: Python
Classifier: Programming Language :: Cython
Classifier: Programming Language :: Python :: 3
Classifier: Programming Language :: Python :: 3 :: Only
Classifier: Programming Language :: Python :: 3.5
Classifier: Programming Language :: Python :: 3.6
Classifier: Programming Language :: Python :: 3.7
Classifier: Programming Language :: Python :: 3.8
Classifier: Programming Language :: Python :: 3.9
Classifier: Programming Language :: Python :: 3.10
Classifier: Development Status :: 5 - Production/Stable
Classifier: Framework :: Pytest
Classifier: Typing :: Typed
Classifier: Intended Audience :: Developers
Classifier: License :: OSI Approved :: Apache Software License
Requires-Python: >=3.5
License-File: LICENSE
License-File: NOTICE
Requires-Dist: pytest (>=6.0.0)
Requires-Dist: attrs (>=19.2.0)
Requires-Dist: psutil (>=5.0.0)
Requires-Dist: typing-extensions
Requires-Dist: pytest-skip-markers
Provides-Extra: changelog
Requires-Dist: towncrier (==21.9.0rc1) ; extra == 'changelog'
Provides-Extra: docs
Requires-Dist: furo ; extra == 'docs'
Requires-Dist: sphinx ; extra == 'docs'
Requires-Dist: sphinx-copybutton ; extra == 'docs'
Requires-Dist: sphinx-prompt ; extra == 'docs'
Requires-Dist: sphinxcontrib-spelling ; extra == 'docs'
Requires-Dist: sphinxcontrib-towncrier (>=0.2.1a0) ; extra == 'docs'
Provides-Extra: lint
Requires-Dist: pylint (==2.7.4) ; extra == 'lint'
Requires-Dist: pyenchant ; extra == 'lint'
Requires-Dist: black ; (python_version >= "3.7") and extra == 'lint'
Requires-Dist: reorder-python-imports ; (python_version >= "3.7") and extra == 'lint'
Provides-Extra: tests
Requires-Dist: pytest-subtests ; extra == 'tests'
